jakubsulla/__init__.py
jakubsulla/functions.py
jakubsulla/xmr_pool-eu.py
jakubsulla-1.1.1.dist-info/LICENSE
jakubsulla-1.1.1.dist-info/METADATA
jakubsulla-1.1.1.dist-info/WHEEL
jakubsulla-1.1.1.dist-info/top_level.txt
jakubsulla-1.1.1.dist-info/RECORD
