Metadata-Version: 2.1
Name: jakubsulla
Version: 1.1.1
Summary: basic useful tools
Home-page: UNKNOWN
Author: Jakubsulla (Jakub Šulla)
Author-email: <support@jakubsulla.tk>
License: UNKNOWN
Keywords: python,tools,simple,hello,testing
Platform: UNKNOWN
Classifier: Development Status :: 1 - Planning
Classifier: Intended Audience :: Developers
Classifier: Programming Language :: Python :: 3
Classifier: Operating System :: Unix
Classifier: Operating System :: MacOS :: MacOS X
Classifier: Operating System :: Microsoft :: Windows
License-File: LICENSE
Requires-Dist: bs4
